exam/exam.py
podval/__init__.py
podval/enelp.py
podval/gamal.py
podval/mypy_plugin.py
podval/pcay.py
podval/char/__init__.py
podval/char/__init__.pyi
podval/compat/__init__.py
podval/compat/py3k.py
podval/compat/tests/__init__.py
podval/core/__init__.py
podval/core/__init__.pyi
podval/core/_dtype.py
podval/core/_dtype_ctypes.py
podval/core/_internal.py
podval/core/_multiarray_umath.py
podval/core/_utils.py
podval/core/arrayprint.py
podval/core/defchararray.py
podval/core/einsumfunc.py
podval/core/fromnumeric.py
podval/core/function_base.py
podval/core/getlimits.py
podval/core/multiarray.py
podval/core/numeric.py
podval/core/numerictypes.py
podval/core/overrides.py
podval/core/records.py
podval/core/shape_base.py
podval/core/umath.py
podval/distutils/__init__.py
podval/distutils/__init__.pyi
podval/distutils/_shell_utils.py
podval/distutils/armccompiler.py
podval/distutils/ccompiler.py
podval/distutils/ccompiler_opt.py
podval/distutils/conv_template.py
podval/distutils/core.py
podval/distutils/cpuinfo.py
podval/distutils/exec_command.py
podval/distutils/extension.py
podval/distutils/from_template.py
podval/distutils/fujitsuccompiler.py
podval/distutils/intelccompiler.py
podval/distutils/lib2def.py
podval/distutils/line_endings.py
podval/distutils/log.py
podval/distutils/mingw32ccompiler.py
podval/distutils/misc_util.py
podval/distutils/msvc9compiler.py
podval/distutils/msvccompiler.py
podval/distutils/npy_pkg_config.py
podval/distutils/numpy_distribution.py
podval/distutils/pathccompiler.py
podval/distutils/system_info.py
podval/distutils/unixccompiler.py
podval/distutils/checks/cpu_asimd.c
podval/distutils/checks/cpu_asimddp.c
podval/distutils/checks/cpu_asimdfhm.c
podval/distutils/checks/cpu_asimdhp.c
podval/distutils/checks/cpu_avx.c
podval/distutils/checks/cpu_avx2.c
podval/distutils/checks/cpu_avx512_clx.c
podval/distutils/checks/cpu_avx512_cnl.c
podval/distutils/checks/cpu_avx512_icl.c
podval/distutils/checks/cpu_avx512_knl.c
podval-12.0.dist-info/METADATA
podval-12.0.dist-info/WHEEL
podval-12.0.dist-info/top_level.txt
podval-12.0.dist-info/RECORD
