Metadata-Version: 2.1
Name: podval
Version: 12.0
Summary: Discr
Author: VipesPras
